chord_lib/__init__.py
chord_lib/ingestion.py
chord_lib/package.cfg
chord_lib/workflows.py
chord_lib/auth/__init__.py
chord_lib/auth/django_remote_user.py
chord_lib/auth/flask_decorators.py
chord_lib/auth/headers.py
chord_lib/auth/roles.py
chord_lib/events/__init__.py
chord_lib/events/notifications.py
chord_lib/events/types.py
chord_lib/responses/__init__.py
chord_lib/responses/errors.py
chord_lib/responses/flask_errors.py
chord_lib/schemas/__init__.py
chord_lib/schemas/_utils.py
chord_lib/schemas/chord.py
chord_lib/schemas/chord_data_use.schema.json
chord_lib/schemas/chord_ingest.schema.json
chord_lib/schemas/ga4gh.py
chord_lib/schemas/ga4gh_service_info.schema.json
chord_lib/search/__init__.py
chord_lib/search/data_structure.py
chord_lib/search/operations.py
chord_lib/search/postgres.py
chord_lib/search/queries.py
tests/__init__.py
tests/django_settings.py
tests/test_events.py
tests/test_ingestion.py
tests/test_platform_django.py
tests/test_platform_flask.py
tests/test_responses.py
tests/test_search.py
tests/test_workflows.py
chord_lib-0.9.0.dist-info/LICENSE
chord_lib-0.9.0.dist-info/METADATA
chord_lib-0.9.0.dist-info/WHEEL
chord_lib-0.9.0.dist-info/top_level.txt
chord_lib-0.9.0.dist-info/RECORD
