Metadata-Version: 2.1
Name: chord-lib
Version: 0.9.0
Summary: A set of common utilities and helpers for CHORD.
Home-page: https://github.com/c3g/chord_lib
Author: David Lougheed
Author-email: david.lougheed@mail.mcgill.ca
License: LGPLv3
Platform: UNKNOWN
Classifier: Programming Language :: Python :: 3
Classifier: License :: OSI Approved :: GNU Lesser General Public License v3 (LGPLv3)
Classifier: Operating System :: OS Independent
Requires-Python: >=3.6
Requires-Dist: jsonschema (<4,>=3.2.0)
Requires-Dist: psycopg2-binary (<3.0,>=2.8.5)
Requires-Dist: redis (<4.0,>=3.5.1)
Requires-Dist: Werkzeug (<2.0,>=1.0.1)
Provides-Extra: django
Requires-Dist: Django (<3.0,>=2.2.12) ; extra == 'django'
Requires-Dist: djangorestframework (<3.12,>=3.11) ; extra == 'django'
Provides-Extra: flask
Requires-Dist: Flask (<2.0,>=1.1.2) ; extra == 'flask'
